{
  "addresses": [
    {
      "id": "2",
      "title": "Teste 3",
      "street": "Rua Miguel Metnek",
      "complement": "",
      "neighborhood": "Pinheirinho",
      "city": "Curitiba",
      "state": "PR",
      "zipcode": "81150-220",
      "created_at": "2024-04-17T12:00:00",
      "updated_at": "2024-04-18T20:58:48.784Z"
    },
    {
      "id": "436b",
      "title": "Trabalho-Jhon",
      "zipcode": "82210110",
      "street": "Rua Walter Guimarães da Costa",
      "complement": "",
      "neighborhood": "São Lourenço",
      "city": "Curitiba",
      "state": "PR",
      "created_at": "2024-04-18T01:58:22.681Z",
      "updated_at": "2024-04-18T19:42:44.836Z"
    },
    {
      "id": "ab26",
      "title": "Trabalho 70",
      "zipcode": "83323-400",
      "street": "Rua Wanda dos Santos Mallmann",
      "complement": "até 935/936",
      "neighborhood": "Centro",
      "city": "Pinhais",
      "state": "PR",
      "created_at": "2024-04-18T10:22:36.353Z",
      "updated_at": "2024-04-18T18:50:55.016Z"
    },
    {
      "id": "0808",
      "title": "Teste 3",
      "zipcode": "81650-220",
      "street": "Rua Antônio Schiebel",
      "complement": "até 1299/1300",
      "neighborhood": "Boqueirão",
      "city": "Curitiba",
      "state": "PR",
      "created_at": "2024-04-18T10:45:10.503Z",
      "updated_at": "2024-04-18T10:45:10.503Z"
    },
    {
      "id": "cf2b",
      "title": "Casa 2",
      "zipcode": "81650210",
      "street": "Rua Napoleão Laureano",
      "complement": "",
      "neighborhood": "Boqueirão",
      "city": "Curitiba",
      "state": "PR",
      "created_at": "2024-04-18T11:05:50.187Z",
      "updated_at": "2024-04-18T11:06:15.474Z"
    },
    {
      "id": "feec",
      "title": "Mais 1",
      "zipcode": "81650230",
      "street": "Rua Salvador Ferrante",
      "complement": "até 1229/1230",
      "neighborhood": "Boqueirão",
      "city": "Curitiba",
      "state": "PR",
      "created_at": "2024-04-18T11:26:22.706Z",
      "updated_at": "2024-04-18T11:26:22.706Z"
    },
    {
      "id": "5db2",
      "title": "Teste 4",
      "zipcode": "81720110",
      "street": "Rua Clara Tedesco",
      "complement": "de 3071/3072 ao fim",
      "neighborhood": "Xaxim",
      "city": "Curitiba",
      "state": "PR",
      "created_at": "2024-04-18T13:25:23.923Z",
      "updated_at": "2024-04-18T13:25:23.923Z"
    },
    {
      "id": "9067",
      "title": "Sei la",
      "zipcode": "81650-220",
      "street": "Rua Antônio Schiebel",
      "complement": "até 1299/1300",
      "neighborhood": "Boqueirão",
      "city": "Curitiba",
      "state": "PR",
      "created_at": "2024-04-19T02:17:28.890Z",
      "updated_at": "2024-04-19T02:17:28.890Z"
    }
  ]
}